ogsapi/__init__.py
ogsapi/client.py
ogsapi/ogs_api_exception.py
ogsapi/ogscredentials.py
ogsapi/ogsgame.py
ogsapi/ogsgameclock.py
ogsapi/ogsgamedata.py
ogsapi/ogsrestapi.py
ogsapi/ogssocket.py
ogsapi/py.typed
tests/test.py
ogsapi-1.3.0.dist-info/LICENSE
ogsapi-1.3.0.dist-info/METADATA
ogsapi-1.3.0.dist-info/WHEEL
ogsapi-1.3.0.dist-info/top_level.txt
ogsapi-1.3.0.dist-info/RECORD
