Metadata-Version: 2.1
Name: ogsapi
Version: 1.3.0
Summary: An API Wrapper for online-go.com, an online Go / Baduk server
Author-email: Dakota Marshall <me@dakotamarshall.net>
License: GNU GENERAL PUBLIC LICENSE
Project-URL: Homepage, https://gitlab.com/dakota.marshall/ogs-python
Project-URL: Repository, https://gitlab.com/dakota.marshall/ogs-python
Project-URL: Documentation, https://ogs-python.dakotamarshall.net/
Project-URL: Changelog, https://gitlab.com/dakota.marshall/ogs-python/-/blob/prod/CHANGELOG.md
Classifier: Programming Language :: Python :: 3
Classifier: License :: OSI Approved :: GNU General Public License v3 (GPLv3)
Classifier: Operating System :: OS Independent
Requires-Python: >=3.7
License-File: LICENSE
Requires-Dist: python-engineio ==3.13.2
Requires-Dist: python-socketio ==4.6.0
Requires-Dist: websocket-client
Requires-Dist: requests
Requires-Dist: loguru
